LICENSE
MANIFEST.in
README.md
setup.py
django_newsletters.egg-info/PKG-INFO
django_newsletters.egg-info/SOURCES.txt
django_newsletters.egg-info/dependency_links.txt
django_newsletters.egg-info/requires.txt
django_newsletters.egg-info/top_level.txt
newsletters/__init__.py
newsletters/admin.py
newsletters/forms.py
newsletters/models.py
newsletters/permissions.py
newsletters/rest_views.py
newsletters/serializers.py
newsletters/urls.py
newsletters/utils.py
newsletters/views.py
newsletters/migrations/0001_initial.py
newsletters/migrations/0002_auto_20150630_0009.py
newsletters/migrations/0003_auto_20150701_1840.py
newsletters/migrations/__init__.py
newsletters/tests/__init__.py
newsletters/tests/runtests.py
newsletters/tests/test.py