Metadata-Version: 1.1
Name: django-newsletters
Version: 0.0.3
Summary: Template for reusable django applications.
Home-page: https://github.com/byteweaver/django-newsletters
Author: byteweaver
Author-email: contact@byteweaver.org
License: BSD
Platform: UNKNOWN
Classifier: Development Status :: 1 - Planning
Classifier: Environment :: Web Environment
Classifier: Intended Audience :: Developers
Classifier: Framework :: Django
Classifier: License :: OSI Approved :: BSD License
Classifier: Operating System :: OS Independent
Classifier: Programming Language :: Python
